translate_missing/__init__.py
translate_missing/translate_missing.py
translate_missing-0.1.0.dist-info/licenses/LICENSE
translate_missing-0.1.0.dist-info/METADATA
translate_missing-0.1.0.dist-info/WHEEL
translate_missing-0.1.0.dist-info/entry_points.txt
translate_missing-0.1.0.dist-info/top_level.txt
translate_missing-0.1.0.dist-info/RECORD
