Metadata-Version: 2.4
Name: translate-missing
Version: 0.1.0
Summary: A simple tool to find and translate missing keys in i18next localization files.
Home-page: https://github.com/jbelew/translate-missing
Author: John Belew
Author-email: john.belew@gmail.com
License: GPL-3.0
Classifier: Programming Language :: Python :: 3
Classifier: License :: OSI Approved :: GNU General Public License v3 (GPLv3)
Classifier: Operating System :: OS Independent
License-File: LICENSE
Requires-Dist: deep_translator
Dynamic: author
Dynamic: author-email
Dynamic: classifier
Dynamic: description
Dynamic: description-content-type
Dynamic: home-page
Dynamic: license
Dynamic: license-file
Dynamic: requires-dist
Dynamic: summary
